<?xml version="1.0"?>
<screenshots>
  <image>
    <filename>001.jpg</filename>
    <description>g</description>
    <width>799</width>
    <height>499</height>
    <thumbnail>
      <filename>001.jpg</filename>
      <title>g</title>
    </thumbnail>
  </image>
  <image>
    <filename>002.jpg</filename>
    <description>
    </description>
    <width>799</width>
    <height>499</height>
    <thumbnail>
      <filename>002.jpg</filename>
      <title>
      </title>
    </thumbnail>
  </image>
  <image>
    <filename>003.jpg</filename>
    <description>
    </description>
    <width>799</width>
    <height>499</height>
    <thumbnail>
      <filename>003.jpg</filename>
      <title>
      </title>
    </thumbnail>
  </image>
  <image>
    <filename>004.jpg</filename>
    <description>
    </description>
    <width>799</width>
    <height>499</height>
    <thumbnail>
      <filename>004.jpg</filename>
      <title>
      </title>
    </thumbnail>
  </image>
  <image>
    <filename>005.jpg</filename>
    <description>
    </description>
    <width>799</width>
    <height>499</height>
    <thumbnail>
      <filename>005.jpg</filename>
      <title>
      </title>
    </thumbnail>
  </image>
  <image>
    <filename>006.jpg</filename>
    <description>
    </description>
    <width>799</width>
    <height>499</height>
    <thumbnail>
      <filename>006.jpg</filename>
      <title>
      </title>
    </thumbnail>
  </image>
  <image>
    <filename>007.jpg</filename>
    <description>
    </description>
    <width>799</width>
    <height>499</height>
    <thumbnail>
      <filename>007.jpg</filename>
      <title>
      </title>
    </thumbnail>
  </image>
  <image>
    <filename>008.jpg</filename>
    <description>
    </description>
    <width>799</width>
    <height>499</height>
    <thumbnail>
      <filename>008.jpg</filename>
      <title>
      </title>
    </thumbnail>
  </image>
  <image>
    <filename>009.jpg</filename>
    <description>
    </description>
    <width>799</width>
    <height>499</height>
    <thumbnail>
      <filename>009.jpg</filename>
      <title>
      </title>
    </thumbnail>
  </image>
  <image>
    <filename>010.jpg</filename>
    <description>
    </description>
    <width>799</width>
    <height>499</height>
    <thumbnail>
      <filename>010.jpg</filename>
      <title>
      </title>
    </thumbnail>
  </image>
  <image>
    <filename>011.jpg</filename>
    <description>
    </description>
    <width>799</width>
    <height>499</height>
    <thumbnail>
      <filename>011.jpg</filename>
      <title>
      </title>
    </thumbnail>
  </image>
  <image>
    <filename>012.jpg</filename>
    <description>
    </description>
    <width>799</width>
    <height>499</height>
    <thumbnail>
      <filename>012.jpg</filename>
      <title>
      </title>
    </thumbnail>
  </image>
  <image>
    <filename>013.jpg</filename>
    <description>
    </description>
    <width>799</width>
    <height>499</height>
    <thumbnail>
      <filename>013.jpg</filename>
      <title>
      </title>
    </thumbnail>
  </image>
  <image>
    <filename>014.jpg</filename>
    <description>
    </description>
    <width>799</width>
    <height>499</height>
    <thumbnail>
      <filename>014.jpg</filename>
      <title>
      </title>
    </thumbnail>
  </image>
  <image>
    <filename>015.jpg</filename>
    <description>
    </description>
    <width>799</width>
    <height>499</height>
    <thumbnail>
      <filename>015.jpg</filename>
      <title>
      </title>
    </thumbnail>
  </image>
  <image>
    <filename>016.jpg</filename>
    <description>
    </description>
    <width>799</width>
    <height>499</height>
    <thumbnail>
      <filename>016.jpg</filename>
      <title>
      </title>
    </thumbnail>
  </image>
  <image>
    <filename>017.jpg</filename>
    <description>
    </description>
    <width>799</width>
    <height>499</height>
    <thumbnail>
      <filename>017.jpg</filename>
      <title>
      </title>
    </thumbnail>
  </image>
  <image>
    <filename>018.jpg</filename>
    <description>
    </description>
    <width>799</width>
    <height>499</height>
    <thumbnail>
      <filename>018.jpg</filename>
      <title>
      </title>
    </thumbnail>
  </image>
  <image>
    <filename>019.jpg</filename>
    <description>
    </description>
    <width>799</width>
    <height>499</height>
    <thumbnail>
      <filename>019.jpg</filename>
      <title>
      </title>
    </thumbnail>
  </image>
  <image>
    <filename>020.jpg</filename>
    <description>
    </description>
    <width>799</width>
    <height>499</height>
    <thumbnail>
      <filename>020.jpg</filename>
      <title>
      </title>
    </thumbnail>
  </image>
  <image>
    <filename>021.jpg</filename>
    <description>
    </description>
    <width>799</width>
    <height>499</height>
    <thumbnail>
      <filename>021.jpg</filename>
      <title>
      </title>
    </thumbnail>
  </image>
  <image>
    <filename>022.jpg</filename>
    <description>
    </description>
    <width>799</width>
    <height>499</height>
    <thumbnail>
      <filename>022.jpg</filename>
      <title>
      </title>
    </thumbnail>
  </image>
  <image>
    <filename>023.jpg</filename>
    <description>
    </description>
    <width>799</width>
    <height>499</height>
    <thumbnail>
      <filename>023.jpg</filename>
      <title>
      </title>
    </thumbnail>
  </image>
  <image>
    <filename>024.jpg</filename>
    <description>
    </description>
    <width>799</width>
    <height>499</height>
    <thumbnail>
      <filename>024.jpg</filename>
      <title>
      </title>
    </thumbnail>
  </image>
  <image>
    <filename>025.jpg</filename>
    <description>
    </description>
    <width>799</width>
    <height>499</height>
    <thumbnail>
      <filename>025.jpg</filename>
      <title>
      </title>
    </thumbnail>
  </image>
  <image>
    <filename>026.jpg</filename>
    <description>
    </description>
    <width>799</width>
    <height>499</height>
    <thumbnail>
      <filename>026.jpg</filename>
      <title>
      </title>
    </thumbnail>
  </image>
  <image>
    <filename>027.jpg</filename>
    <description>
    </description>
    <width>799</width>
    <height>499</height>
    <thumbnail>
      <filename>027.jpg</filename>
      <title>
      </title>
    </thumbnail>
  </image>
  <image>
    <filename>028.jpg</filename>
    <description>
    </description>
    <width>799</width>
    <height>499</height>
    <thumbnail>
      <filename>028.jpg</filename>
      <title>
      </title>
    </thumbnail>
  </image>
  <image>
    <filename>029.jpg</filename>
    <description>
    </description>
    <width>799</width>
    <height>499</height>
    <thumbnail>
      <filename>029.jpg</filename>
      <title>
      </title>
    </thumbnail>
  </image>
  <image>
    <filename>030.jpg</filename>
    <description>
    </description>
    <width>799</width>
    <height>499</height>
    <thumbnail>
      <filename>030.jpg</filename>
      <title>
      </title>
    </thumbnail>
  </image>
  <image>
    <filename>031.jpg</filename>
    <description>
    </description>
    <width>799</width>
    <height>499</height>
    <thumbnail>
      <filename>031.jpg</filename>
      <title>
      </title>
    </thumbnail>
  </image>
  <image>
    <filename>032.jpg</filename>
    <description>
    </description>
    <width>799</width>
    <height>499</height>
    <thumbnail>
      <filename>032.jpg</filename>
      <title>
      </title>
    </thumbnail>
  </image>
  <image>
    <filename>033.jpg</filename>
    <description>
    </description>
    <width>799</width>
    <height>499</height>
    <thumbnail>
      <filename>033.jpg</filename>
      <title>
      </title>
    </thumbnail>
  </image>
  <image>
    <filename>034.jpg</filename>
    <description>
    </description>
    <width>799</width>
    <height>499</height>
    <thumbnail>
      <filename>034.jpg</filename>
      <title>
      </title>
    </thumbnail>
  </image>
  <image>
    <filename>035.jpg</filename>
    <description>
    </description>
    <width>799</width>
    <height>499</height>
    <thumbnail>
      <filename>035.jpg</filename>
      <title>
      </title>
    </thumbnail>
  </image>
  <image>
    <filename>036.jpg</filename>
    <description>
    </description>
    <width>799</width>
    <height>499</height>
    <thumbnail>
      <filename>036.jpg</filename>
      <title>
      </title>
    </thumbnail>
  </image>
  <image>
    <filename>037.jpg</filename>
    <description>
    </description>
    <width>799</width>
    <height>499</height>
    <thumbnail>
      <filename>037.jpg</filename>
      <title>
      </title>
    </thumbnail>
  </image>
  <image>
    <filename>038.jpg</filename>
    <description>
    </description>
    <width>799</width>
    <height>499</height>
    <thumbnail>
      <filename>038.jpg</filename>
      <title>
      </title>
    </thumbnail>
  </image>
  <image>
    <filename>039.jpg</filename>
    <description>
    </description>
    <width>799</width>
    <height>499</height>
    <thumbnail>
      <filename>039.jpg</filename>
      <title>
      </title>
    </thumbnail>
  </image>
  <image>
    <filename>040.jpg</filename>
    <description>y</description>
    <width>799</width>
    <height>499</height>
    <thumbnail>
      <filename>040.jpg</filename>
      <title>y</title>
    </thumbnail>
  </image>
</screenshots>